src/__init__.py
src/wpcli.py
src/xwppy.py
xwppy-0.1.dist-info/LICENSE
xwppy-0.1.dist-info/METADATA
xwppy-0.1.dist-info/WHEEL
xwppy-0.1.dist-info/top_level.txt
xwppy-0.1.dist-info/RECORD
