Metadata-Version: 2.1
Name: xwppy
Version: 0.1
Summary: A wordpress python to CLI conversion library
Home-page: https://github.com/adv-ai-tech/xwppy
Author: Advait Lab
Author-email: contact@advaitlabs.com
License: MIT
Platform: UNKNOWN
Requires-Dist: os
